{
  "month": "2026-02",
  "timezone": "Asia/Hong_Kong",
  "resetHour": 8,
  "note": "Community-provided February 2026 Daily Challenge list. Discord emoji/custom emoji notes were removed; shorthand entries such as PH1, Marathon (...), why370, Rare Apperarance, and Lazy Passenger were normalized.",
  "days": [
    { "date": "2026-02-01", "event": "Rush Hour", "routeCode": "476E", "race": true },
    { "date": "2026-02-02", "event": "Private Hire", "routeCode": "PH1", "race": false },
    { "date": "2026-02-03", "event": "Marathon Road Closure", "routeCode": "370", "race": false },
    { "date": "2026-02-04", "event": "Foggy Day", "routeCode": "148W", "race": false },
    { "date": "2026-02-05", "event": "Marathon Road Closure", "routeCode": "242", "race": false },
    { "date": "2026-02-06", "event": "Concert Crowd Dispersal", "routeCode": "140E", "race": false },
    { "date": "2026-02-07", "event": "Rare Appearance", "routeCode": "476", "race": true },
    { "date": "2026-02-08", "event": "Rush Hour", "routeCode": "74AS", "race": true },
    { "date": "2026-02-09", "event": "Private Hire", "routeCode": "PH1", "race": false },
    { "date": "2026-02-10", "event": "Marathon Road Closure", "routeCode": "N146A", "race": false },
    { "date": "2026-02-11", "event": "Marathon Road Closure", "routeCode": "270A", "race": false },
    { "date": "2026-02-12", "event": "Marathon Shuttle", "routeCode": "R148", "race": false },
    { "date": "2026-02-13", "event": "Marathon Shuttle", "routeCode": "R148", "race": false },
    { "date": "2026-02-14", "event": "Rare Appearance x Private Hire", "routeCode": "PH", "race": true },
    { "date": "2026-02-15", "event": "Rare Appearance x Private Hire", "routeCode": "PH", "race": true },
    { "date": "2026-02-16", "event": "Urban Odyssey", "routeCode": "77X", "race": true },
    { "date": "2026-02-17", "event": "Safety First", "routeCode": "142", "race": true },
    { "date": "2026-02-18", "event": "Marathon Road Closure", "routeCode": "Y370", "race": false },
    { "date": "2026-02-19", "event": "Bridge Closure", "routeCode": "25Y", "race": false },
    { "date": "2026-02-20", "event": "Grumble Day", "routeCode": "N171W", "race": false },
    { "date": "2026-02-21", "event": "Rare Appearance", "routeCode": "46W", "race": true },
    { "date": "2026-02-22", "event": "Rush Hour", "routeCode": "370BW", "race": true },
    { "date": "2026-02-23", "event": "Marathon Road Closure", "routeCode": "248", "race": false },
    { "date": "2026-02-24", "event": "Lazy Passengers", "routeCode": "41AS", "race": false },
    { "date": "2026-02-25", "event": "Private Hire", "routeCode": "PH1", "race": false },
    { "date": "2026-02-26", "event": "Marathon Road Closure", "routeCode": "473", "race": false },
    { "date": "2026-02-27", "event": "Rare Appearance x Private Hire", "routeCode": "PH", "race": false },
    { "date": "2026-02-28", "event": "Marathon Shuttle", "routeCode": "R148", "race": true }
  ]
}
