{
  "id": "673",
  "number": "673",
  "operators": [
    "HZ",
    "CSB"
  ],
  "category": "inner",
  "pattern": "circular",
  "zones": [
    6,
    7,
    8
  ],
  "origin": {
    "zh": "East Factory",
    "en": "East Factory"
  },
  "destination": {
    "zh": "East Door Bus Terminus / 東廠",
    "en": "East Door Bus Terminus / 東廠"
  },
  "via": {
    "zh": "Leafy Hospital, Leafy Bay, Praya YiYan Road, Haisey (→Zone 8)",
    "en": "Leafy Hospital, Leafy Bay, Praya YiYan Road, Haisey (→Zone 8)"
  },
  "interval": {
    "zh": "30 - 90 mins",
    "en": "30 - 90 mins"
  },
  "journeyTime": {
    "zh": "20 mins",
    "en": "20 mins"
  },
  "fare": "$9.4",
  "levelRequired": 72,
  "length": {
    "zh": "15.7 km",
    "en": "15.7 km"
  },
  "stops": [
    {
      "direction": {
        "zh": "方向1（海怡車廠 → 海怡車廠）",
        "en": "Direction 1 (Horizon Depot → Horizon Depot)"
      },
      "serviceTime": {
        "zh": "Mon – Fri: 07:20 – 18:00 / Sat, Sun and PH: 09:00 – 18:00",
        "en": "Mon – Fri: 07:20 – 18:00 / Sat, Sun and PH: 09:00 – 18:00"
      },
      "list": [
        {
          "name": {
            "zh": "海怡車廠",
            "en": "Horizon Depot"
          },
          "zone": 6
        },
        {
          "name": {
            "zh": "海怡西",
            "en": "West Horizon"
          }
        },
        {
          "name": {
            "zh": "海怡摩天大廈",
            "en": "Horizon Tower"
          }
        },
        {
          "name": {
            "zh": "海怡沙灘",
            "en": "Horizon Beach"
          }
        },
        {
          "name": {
            "zh": "第七區轉車站",
            "en": "Senpai Bypass"
          },
          "zone": 7
        },
        {
          "name": {
            "zh": "東廠",
            "en": "East Factory"
          },
          "zone": 7
        },
        {
          "name": {
            "zh": "葉欣公園",
            "en": "YiYan Park"
          }
        },
        {
          "name": {
            "zh": "鑽石交易塔",
            "en": "Diamond Trading Tower"
          }
        },
        {
          "name": {
            "zh": "新地花園",
            "en": "Sindy Garden"
          }
        },
        {
          "name": {
            "zh": "葉角灣",
            "en": "Leafy Bay"
          },
          "zone": 7
        },
        {
          "name": {
            "zh": "葉角灣墳場",
            "en": "Leafy Bay Cemetery"
          }
        },
        {
          "name": {
            "zh": "葉角醫院",
            "en": "Leafy Hospital"
          }
        },
        {
          "name": {
            "zh": "東門總站",
            "en": "East Door Bus Terminus"
          },
          "zone": 7
        },
        {
          "name": {
            "zh": "海西角",
            "en": "Haisey Point"
          },
          "zone": 8
        },
        {
          "name": {
            "zh": "海西邨",
            "en": "Haisey Estate"
          }
        },
        {
          "name": {
            "zh": "葉角醫院",
            "en": "Leafy Hospital"
          },
          "zone": 7
        },
        {
          "name": {
            "zh": "葉角灣墳場",
            "en": "Leafy Bay Cemetery"
          }
        },
        {
          "name": {
            "zh": "葉角灣",
            "en": "Leafy Bay"
          }
        },
        {
          "name": {
            "zh": "新地花園",
            "en": "Sindy Garden"
          },
          "zone": 7
        },
        {
          "name": {
            "zh": "葉欣海旁道",
            "en": "Praya YiYan Road"
          }
        },
        {
          "name": {
            "zh": "南洋大廈",
            "en": "Southern Building"
          }
        },
        {
          "name": {
            "zh": "彩虹廣場",
            "en": "Rainbow Plaza"
          }
        },
        {
          "name": {
            "zh": "山道",
            "en": "YiYan Road"
          }
        },
        {
          "name": {
            "zh": "第七區轉車站",
            "en": "Axis Road"
          },
          "zone": 7
        },
        {
          "name": {
            "zh": "海怡沙灘",
            "en": "Horizon Beach"
          },
          "zone": 6
        },
        {
          "name": {
            "zh": "海怡摩天大廈",
            "en": "Horizon Tower"
          }
        },
        {
          "name": {
            "zh": "海怡西",
            "en": "West Horizon"
          }
        },
        {
          "name": {
            "zh": "海怡車廠",
            "en": "Horizon Depot"
          }
        }
      ]
    }
  ],
  "wikiUrl": "https://sunshine-islands-roblox.fandom.com/wiki/Bus_route_673"
}